gaspery/__init__.py
gaspery/calculate_fi.py
gaspery/strategies.py
gaspery/utils.py
gaspery-0.3.0.dist-info/METADATA
gaspery-0.3.0.dist-info/WHEEL
gaspery-0.3.0.dist-info/licenses/LICENSE
gaspery-0.3.0.dist-info/RECORD
