Metadata-Version: 2.3
Name: gaspery
Version: 0.3.0
Summary: Fisher Information-based radial velocity observation scheduling
Project-URL: Homepage, https://github.com/cl3425/gaspery
Project-URL: Bug Tracker, https://github.com/cl3425/gaspery/issues
Author-email: Christopher Lam <c.lam@ufl.edu>
License-File: LICENSE
Classifier: License :: OSI Approved :: MIT License
Classifier: Operating System :: OS Independent
Classifier: Programming Language :: Python :: 3
Requires-Python: >=3.7
